kuaikuai/__main__.py
kuaikuai-1.0.0.dist-info/METADATA
kuaikuai-1.0.0.dist-info/WHEEL
kuaikuai-1.0.0.dist-info/RECORD
